kugel/__init__.py
kugel/main.py
kugel/api/__init__.py
kugel/impl/__init__.py
kugel/impl/builtins.yaml
kugel/impl/engine.py
kugel/impl/helpers.py
kugel/impl/jross.py
kugel/impl/registry.py
kugel/impl/tables.py
kugel/impl/time.py
kugel/impl/utils.py
kugel/model/__init__.py
kugel/model/age.py
kugel/model/config.py
kugel/model/constants.py
tests/__init__.py
tests/conftest.py
tests/test_cli.py
tests/test_config.py
tests/test_jobs.py
tests/test_misc.py
tests/test_nodes.py
tests/test_pods.py
tests/test_utils.py
tests/testing.py
kugel-0.1.2.dist-info/LICENSE
kugel-0.1.2.dist-info/METADATA
kugel-0.1.2.dist-info/WHEEL
kugel-0.1.2.dist-info/entry_points.txt
kugel-0.1.2.dist-info/top_level.txt
kugel-0.1.2.dist-info/RECORD
