Metadata-Version: 2.1
Name: kugel
Version: 0.1.2
Summary: Explore Kubernetes resources using SQLite
Home-page: https://github.com/jonross/kugel
Author: Jonathan Ross
Author-email: jonross@alum.mit.edu
Classifier: Programming Language :: Python :: 3
Classifier: License :: OSI Approved :: MIT License
Classifier: Operating System :: OS Independent
Requires-Python: >=3.9
License-File: LICENSE
Requires-Dist: arrow==1.2.0
Requires-Dist: funcy==1.17
Requires-Dist: jmespath==1.0.1
Requires-Dist: pydantic==2.6.1
Requires-Dist: pytest-cov==4.1.0
Requires-Dist: pytest==7.1.3
Requires-Dist: pyyaml==6.0.1
Requires-Dist: tabulate==0.9.0
